ez_setup.py
setup.cfg
setup.py
yatel/__init__.py
yatel/cli.py
yatel/client.py
yatel/db.py
yatel/dom.py
yatel/etl.py
yatel/server.py
yatel/stats.py
yatel/typeconv.py
yatel.egg-info/PKG-INFO
yatel.egg-info/SOURCES.txt
yatel.egg-info/dependency_links.txt
yatel.egg-info/entry_points.txt
yatel.egg-info/requires.txt
yatel.egg-info/top_level.txt
yatel/cluster/__init__.py
yatel/cluster/kmeans.py
yatel/qbj/__init__.py
yatel/qbj/core.py
yatel/qbj/functions.py
yatel/qbj/schema.py
yatel/qbj/shell.py
yatel/tests/__init__.py
yatel/tests/core.py
yatel/tests/test_client.py
yatel/tests/test_cluster.py
yatel/tests/test_db.py
yatel/tests/test_dom.py
yatel/tests/test_etl.py
yatel/tests/test_qbj.py
yatel/tests/test_server.py
yatel/tests/test_stats.py
yatel/tests/test_typeconv.py
yatel/tests/test_weight.py
yatel/tests/test_yio.py
yatel/weight/__init__.py
yatel/weight/core.py
yatel/weight/euclidean.py
yatel/weight/hamming.py
yatel/weight/levenshtein.py
yatel/yio/__init__.py
yatel/yio/core.py
yatel/yio/yjf.py
yatel/yio/yxf.py