Metadata-Version: 1.1
Name: yatel
Version: 0.3
Summary: Yatel allows the creation of user-profile-distance-based of OLAP Network and their multidimensional analysis through a process of exploration.
Home-page: http://getyatel.org
Author: Yatel Team
Author-email: utn_kdd@googlegroups.com
License: WISKEY-WARE
Keywords: Yatel user-profile-distance-based networks  multidimensional
Platform: UNKNOWN
Classifier: Topic :: Utilities
Classifier: License :: OSI Approved :: BSD License
Classifier: Programming Language :: Python :: 2
